<?xml version="1.0" encoding="UTF-8"?><mycoreobject xmlns:xsi="http://www.w3.org/2001/XMLSchema-instance" xmlns:xlink="http://www.w3.org/1999/xlink" ID="domlib_institution_00000221" label="domlib_institution_00000221" version="2.0" xsi:noNamespaceSchemaLocation="datamodel-institution.xsd"><structure/><metadata xml:lang="de"><names class="MCRMetaLangText" heritable="false" notinherit="false"><name xml:lang="en" inherited="0" form="plain">Qäqäma Däbrä Gännät Qəddəst Maryam  / QDGM</name>
</names>
<altnames class="MCRMetaLangText" heritable="false" notinherit="false"><altname xml:lang="en" inherited="0" form="plain">Qäqäma Maryam</altname>
</altnames>
<visitdates class="DLDateInterval" heritable="false" notinherit="false"><visitdate xml:lang="en" inherited="0"><from>2012-06-01</from><to>2012-06-01</to></visitdate>
</visitdates>
<descbys class="MCRMetaLangText" heritable="false" notinherit="false"><descby xml:lang="en" inherited="0" form="plain">D.N.</descby>
</descbys>
<countries class="MCRMetaLangText" heritable="false" notinherit="false"><country xml:lang="en" inherited="0" form="plain">Ethiopia</country>
</countries>
<areas class="MCRMetaLangText" heritable="false" notinherit="false"><area xml:lang="en" inherited="0" form="plain">Tәgray</area>
</areas>
<towns class="MCRMetaLangText" heritable="false" notinherit="false"><town xml:lang="en" inherited="0" form="plain">wäräda Dägˁa Tämben, ṭabiya Mizan, qušät Qäqäma</town>
</towns>
<latitudes class="MCRMetaNumber" heritable="false" notinherit="false"><latitude xml:lang="en" inherited="0">13.5664</latitude>
</latitudes>
<longitudes class="MCRMetaNumber" heritable="false" notinherit="false"><longitude xml:lang="en" inherited="0">39.0586</longitude>
</longitudes>
<altitudes class="MCRMetaNumber" heritable="false" notinherit="false"><altitude xml:lang="en" inherited="0">2122.0</altitude>
</altitudes>
<foundationdates class="MCRMetaISO8601Date" heritable="false" notinherit="false"><foundationdate inherited="0">1400</foundationdate>
</foundationdates>
<foundtodates class="MCRMetaISO8601Date" heritable="false" notinherit="false"><foundtodate inherited="0">1500</foundtodate>
</foundtodates>
<founders class="MCRMetaLangText" heritable="false" notinherit="false"><founder xml:lang="en" inherited="0" form="plain">The old church is said to have been founded by King Zärˀa Yaˁqob (r. 1438-68); the monastic community was established by King Yoḥannəs IV (r. 1872-89).</founder>
</founders>
<conditions class="MCRMetaLangText" heritable="false" notinherit="false"><condition xml:lang="en" inherited="0" form="plain">Gädam. The monastic community consists of at least 15 monks. &#13;
Tabots (7): Mary, Mädḫane ˁAläm, George, (Zä-Mikaˀel) ˀArägawi, Trinity, Kidanä Məḫrät, probably Täklä Haymanot.</condition>
</conditions>
<descriptions class="MCRMetaLangText" heritable="false" notinherit="false"><description xml:lang="en" inherited="0" form="plain">13 Mss. photographed: QDGM-001 ʺThe Four Gospelsʺ; QDGM-002 ʺPraise of Godʺ; QDGM-003 ʺOctateuchʺ; QDGM-004 ʺPsalterʺ; QDGM-005 ʺPraise of Godʺ; QDGM-006 ʺThe Harp of Praiseʺ; QDGM-007 ʺFour Gospelsʺ; QDGM-008 ʺThe Book of the Spirtual Elderʺ; QDGM-009 ʺCommentary to the Pauline Epistlesʺ; QDGM-010 ʺThe History of the Apostlesʺ; QDGM-011 ʺPsalterʺ; QDGM-012 ʺVita of ˀArägawiʺ; QDGM-013 ʺVita of Kirosʺ. The collection includes more than 120 Mss.</description>
</descriptions>
</metadata><service><servdates class="MCRMetaISO8601Date"><servdate inherited="0" type="createdate">2012-06-29T10:16:32.722Z</servdate><servdate inherited="0" type="modifydate">2014-12-21T17:51:24.591Z</servdate></servdates><servflags class="MCRMetaLangText"><servflag xml:lang="en" inherited="0" form="plain" type="creator">DNosnitsin</servflag><servflag xml:lang="en" inherited="0" form="plain" type="editor">DNosnitsin</servflag></servflags><servacls class="MCRMetaAccessRule"><servacl permission="deletedb"><condition format="xml"><boolean operator="and"><boolean operator="or"><condition field="group" operator="=" value="admingroup"/><condition field="group" operator="=" value="ethioadmins"/></boolean><boolean operator="true"/><boolean operator="true"/></boolean></condition></servacl><servacl permission="read"><condition format="xml"><boolean operator="true"/></condition></servacl><servacl permission="writedb"><condition format="xml"><boolean operator="and"><boolean operator="or"><condition field="group" operator="=" value="admingroup"/><condition field="group" operator="=" value="ethioleaders"/></boolean><boolean operator="true"/><boolean operator="true"/></boolean></condition></servacl></servacls></service></mycoreobject>