<?xml version="1.0" encoding="UTF-8"?><mycoreobject xmlns:xsi="http://www.w3.org/2001/XMLSchema-instance" xmlns:xlink="http://www.w3.org/1999/xlink" ID="domlib_institution_00000212" label="domlib_institution_00000212" version="2.0" xsi:noNamespaceSchemaLocation="datamodel-institution.xsd"><structure/><metadata xml:lang="de"><names class="MCRMetaLangText" heritable="false" notinherit="false"><name xml:lang="en" inherited="0" form="plain">ʾƎnda Ḥawaryat Ṗeṭros wä-Ṗawlos / EHPP</name>
</names>
<altnames class="MCRMetaLangText" heritable="false" notinherit="false"><altname xml:lang="en" inherited="0" form="plain">ʾƎnda Ḥawaryat</altname>
</altnames>
<visitdates class="DLDateInterval" heritable="false" notinherit="false"><visitdate xml:lang="en" inherited="0"><from>2011-11-23</from><to>2011-11-23</to></visitdate>
</visitdates>
<descbys class="MCRMetaLangText" heritable="false" notinherit="false"><descby xml:lang="en" inherited="0" form="plain">D.N.</descby>
</descbys>
<countries class="MCRMetaLangText" heritable="false" notinherit="false"><country xml:lang="en" inherited="0" form="plain">Ethiopia</country>
</countries>
<areas class="MCRMetaLangText" heritable="false" notinherit="false"><area xml:lang="en" inherited="0" form="plain">Tǝgray</area>
</areas>
<towns class="MCRMetaLangText" heritable="false" notinherit="false"><town xml:lang="en" inherited="0" form="plain">wäräda Gulo Mäkäda, ṭabiya May Ṣaʿda, qušät ʾEnda Ḥawaryat</town>
</towns>
<latitudes class="MCRMetaNumber" heritable="false" notinherit="false"><latitude xml:lang="en" inherited="0">14.33355</latitude>
</latitudes>
<longitudes class="MCRMetaNumber" heritable="false" notinherit="false"><longitude xml:lang="en" inherited="0">39.501183</longitude>
</longitudes>
<altitudes class="MCRMetaNumber" heritable="false" notinherit="false"><altitude xml:lang="en" inherited="0">2490.0</altitude>
</altitudes>
<foundationdates class="MCRMetaISO8601Date" heritable="false" notinherit="false"><foundationdate inherited="0">1500</foundationdate>
</foundationdates>
<foundtodates class="MCRMetaISO8601Date" heritable="false" notinherit="false"><foundtodate inherited="0">1600</foundtodate>
</foundtodates>
<conditions class="MCRMetaLangText" heritable="false" notinherit="false"><condition xml:lang="en" inherited="0" form="plain">Gätär. &#13;
Tabots (4): Peter and Paul (marble), Mary, Michael, Mäzgäbä Śǝllase (uncertain).&#13;
A small church dedicated to Gäbrä Mänfäs Qǝddus is located in the vicinity.</condition>
</conditions>
<descriptions class="MCRMetaLangText" heritable="false" notinherit="false"><description xml:lang="en" inherited="0" form="plain">17 Mss., one scroll photographed: EHPP-001 “Dawit”; EHPP-002 “Acts of the Apostles”; EHPP-003 “Homily on the Saviour of the World”; EHPP-004 “Vita of Mäzgäbä Śǝllase”; EHPP-005 “Homily on St. Michael”; EHPP-006 “Vita of Gäbrä Mänfäs Qǝddus”; EHPP-007 “Vita of John the Baptist, Miracles of John the Baptist”; EHPP-008 “Homily on St. Michael”; EHPP-009 “The Book of Baptism”; EHPP-010 “Synaxarion (March-September)”; EHPP-011 “Acts of the Apostles”; EHPP-012 “Four Gospels”; EHPP-013 “Book of the Funeral Rite”; EHPP-014 “The Loosening of the Spells”; EHPP-015 “Missal”; EHPP-016 “Homily on the Sabbath of Christians”; EHPP-017 “The Bandlet of Righteous”.</description>
</descriptions>
</metadata><service><servdates class="MCRMetaISO8601Date"><servdate inherited="0" type="createdate">2012-03-19T19:05:50.453Z</servdate><servdate inherited="0" type="modifydate">2014-12-21T18:35:55.005Z</servdate></servdates><servflags class="MCRMetaLangText"><servflag xml:lang="en" inherited="0" form="plain" type="creator">DNosnitsin</servflag><servflag xml:lang="en" inherited="0" form="plain" type="editor">DNosnitsin</servflag></servflags><servacls class="MCRMetaAccessRule"><servacl permission="deletedb"><condition format="xml"><boolean operator="and"><boolean operator="or"><condition field="group" operator="=" value="admingroup"/><condition field="group" operator="=" value="ethioadmins"/></boolean><boolean operator="true"/><boolean operator="true"/></boolean></condition></servacl><servacl permission="read"><condition format="xml"><boolean operator="true"/></condition></servacl><servacl permission="writedb"><condition format="xml"><boolean operator="and"><boolean operator="or"><condition field="group" operator="=" value="admingroup"/><condition field="group" operator="=" value="ethioleaders"/></boolean><boolean operator="true"/><boolean operator="true"/></boolean></condition></servacl></servacls></service></mycoreobject>